cdk_compliant_dynamodb/__init__.py
cdk_compliant_dynamodb/py.typed
cdk_compliant_dynamodb/_jsii/__init__.py
cdk_compliant_dynamodb/_jsii/cdk-compliant-dynamodb@0.0.8.jsii.tgz
cdk_compliant_dynamodb-0.0.8.dist-info/LICENSE
cdk_compliant_dynamodb-0.0.8.dist-info/METADATA
cdk_compliant_dynamodb-0.0.8.dist-info/WHEEL
cdk_compliant_dynamodb-0.0.8.dist-info/top_level.txt
cdk_compliant_dynamodb-0.0.8.dist-info/RECORD
